satxpy.py
satxpy-0.0.1.dist-info/LICENSE
satxpy-0.0.1.dist-info/METADATA
satxpy-0.0.1.dist-info/WHEEL
satxpy-0.0.1.dist-info/top_level.txt
satxpy-0.0.1.dist-info/RECORD
