Metadata-Version: 2.1
Name: satxpy
Version: 0.0.1
Summary: Boolean Expression Builder for SAT Solving
Author-email: Mackenzie High <public@mackenziehigh.com>
Project-URL: Homepage, https://github.com/Mackenzie-High/satxpy
Project-URL: Issues, https://github.com/Mackenzie-High/satxpy/issues
Classifier: Programming Language :: Python :: 3
Classifier: License :: OSI Approved :: MIT License
Classifier: Operating System :: OS Independent
Requires-Python: >=3.10
License-File: LICENSE
